schwi/__init__.py
schwi/app.py
schwi/cli.py
schwi/commands/__init__.py
schwi/commands/basic.py
schwi/commands/chat.py
schwi/runtime/__init__.py
schwi/runtime/command_spec.py
schwi/runtime/context.py
schwi/runtime/project.py
schwi/runtime/renderer.py
schwi/runtime/session.py
schwi/runtime/session_state.py
schwi/runtime/session_store.py
schwi/runtime/settings.py
schwi/runtime/version.py
schwi/ui/__init__.py
schwi/ui/completion.py
schwi/ui/components.py
schwi-0.1.0.dist-info/licenses/LICENSE
schwi-0.1.0.dist-info/WHEEL
schwi-0.1.0.dist-info/entry_points.txt
schwi-0.1.0.dist-info/METADATA
schwi-0.1.0.dist-info/RECORD
