Metadata-Version: 2.4
Name: schwi
Version: 0.1.0
Summary: Add your description here
Author: crlotwhite
Author-email: crlotwhite <crlotwhite@gmail.com>
License-Expression: Apache-2.0
License-File: LICENSE
Requires-Dist: jsonlines>=4.0.0
Requires-Dist: prompt-toolkit>=3.0.52
Requires-Dist: rich>=14.2.0
Requires-Dist: typer>=0.21.1
Requires-Python: >=3.12
